{
  "templates": [
    {
      "id": "1",
      "name": "Бизнес лендинг",
      "description": "Профессиональный шаблон для бизнеса с современным дизайном. Идеально подходит для корпоративных сайтов и сервисов.",
      "author": "Design Studio Pro",
      "license": "MIT",
      "price": 0,
      "keywords": [
        "бизнес",
        "корпоративный",
        "профессиональный",
        "современный"
      ],
      "thumbnail": "https://vitvesti.by/images/2022/08/24/biz.jpg",
      "editableBlocks": [
        {
          "id": "header_title",
          "type": "text",
          "label": "Заголовок страницы",
          "defaultValue": "Добро пожаловать в наш бизнес",
          "required": false
        },
        {
          "id": "header_image",
          "type": "image",
          "label": "Главное изображение",
          "defaultValue": "https://picsum.photos/id/2/1200/600",
          "required": false
        },
        {
          "id": "description",
          "type": "text",
          "label": "Описание компании",
          "defaultValue": "Мы предоставляем лучшие услуги в своей области с 2010 года",
          "required": false
        },
        {
          "id": "contact_info",
          "type": "text",
          "label": "Контактная информация",
          "defaultValue": "Телефон: +7 (999) 999-99-99\nEmail: info@company.com",
          "required": false
        }
      ]
    },
    {
      "id": "2",
      "name": "Портфолио фотографа",
      "description": "Элегантный шаблон для фотографов и творческих личностей. Подчеркивает ваши работы в лучшем свете.",
      "author": "Creative Agency",
      "license": "Commercial",
      "price": 29,
      "keywords": [
        "фотография",
        "портфолио",
        "творческий",
        "галерея",
        "арт"
      ],
      "thumbnail": "https://i.pinimg.com/originals/bf/d5/45/bfd545fbe208315eb52524a2bc274989.jpg",
      "editableBlocks": [
        {
          "id": "photographer_name",
          "type": "text",
          "label": "Имя фотографа",
          "defaultValue": "Иван Иванов",
          "required": false
        },
        {
          "id": "avatar",
          "type": "image",
          "label": "Аватар фотографа",
          "defaultValue": "https://picsum.photos/id/64/200/200",
          "required": false
        },
        {
          "id": "bio",
          "type": "text",
          "label": "Биография",
          "defaultValue": "Профессиональный фотограф с 5-летним опытом. Специализируюсь на портретной и свадебной фотографии.",
          "required": false
        },
        {
          "id": "portfolio_gallery",
          "type": "image",
          "label": "Галерея работ",
          "defaultValue": "https://picsum.photos/id/26/800/600",
          "required": false
        }
      ]
    },
    {
      "id": "3",
      "name": "Интернет-магазин",
      "description": "Современный шаблон для электронной коммерции с удобной навигацией и адаптивным дизайном.",
      "author": "E-Commerce Solutions",
      "license": "Premium",
      "price": 49,
      "keywords": [
        "магазин",
        "e-commerce",
        "продажи",
        "товары",
        "онлайн"
      ],
      "thumbnail": "https://images.steamusercontent.com/ugc/14180816887404947/A5FB8C8D2B0A3F5AA9C5E22EB668B8AC8516DDC2/?imw=512&amp;imh=268&amp;ima=fit&amp;impolicy=Letterbox&amp;imcolor=%23000000&amp;letterbox=true",
      "editableBlocks": [
        {
          "id": "store_name",
          "type": "text",
          "label": "Название магазина",
          "defaultValue": "Мой интернет-магазин",
          "required": false
        },
        {
          "id": "logo",
          "type": "image",
          "label": "Логотип магазина",
          "defaultValue": "https://picsum.photos/id/28/150/150",
          "required": false
        },
        {
          "id": "store_description",
          "type": "text",
          "label": "Описание магазина",
          "defaultValue": "Лучшие товары по доступным ценам с быстрой доставкой по всей стране",
          "required": false
        },
        {
          "id": "featured_products",
          "type": "image",
          "label": "Изображения товаров",
          "defaultValue": "https://picsum.photos/id/27/800/600",
          "required": false
        }
      ]
    },
    {
      "id": "4",
      "name": "Ресторан и кафе",
      "description": "Аппетитный шаблон для ресторанов, кафе и пищевого бизнеса. Вкусный дизайн для вашего меню.",
      "author": "Food Design Studio",
      "license": "Commercial",
      "price": 39,
      "keywords": [
        "ресторан",
        "кафе",
        "еда",
        "меню",
        "кулинария"
      ],
      "thumbnail": "https://mir-s3-cdn-cf.behance.net/projects/max_808/625aa7125535685.Y3JvcCwxMDgwLDg0NCwwLDExNw.png",
      "editableBlocks": [
        {
          "id": "restaurant_name",
          "type": "text",
          "label": "Название заведения",
          "defaultValue": "Ресторан 'Вкуснота'",
          "required": false
        },
        {
          "id": "restaurant_photo",
          "type": "image",
          "label": "Фото заведения",
          "defaultValue": "https://picsum.photos/id/431/1000/600",
          "required": false
        },
        {
          "id": "menu_description",
          "type": "text",
          "label": "Описание меню",
          "defaultValue": "Мы готовим блюда из свежих продуктов по традиционным рецептам",
          "required": false
        },
        {
          "id": "signature_dishes",
          "type": "image",
          "label": "Фото фирменных блюд",
          "defaultValue": "https://picsum.photos/id/312/800/600",
          "required": false
        }
      ]
    }
  ],
  "landings": [
    {
      "templateId": "3",
      "name": "Лендинг: Интернет-магазин",
      "createdAt": "2025-10-29T18:24:30.713Z",
      "blocks": [
        {
          "id": "store_name",
          "type": "text",
          "content": "Мой интернет-магазин",
          "order": 0
        },
        {
          "id": "logo",
          "type": "image",
          "content": "https://picsum.photos/id/28/150/150",
          "order": 1
        },
        {
          "id": "store_description",
          "type": "text",
          "content": "Лучшие товары по доступным ценам с быстрой доставкой по всей стране",
          "order": 2
        },
        {
          "id": "featured_products",
          "type": "image",
          "content": "https://picsum.photos/id/27/800/600",
          "order": 3
        }
      ],
      "id": 1
    },
    {
      "templateId": "2",
      "name": "Лендинг: Портфолио фотографа",
      "createdAt": "2025-10-29T18:24:43.225Z",
      "blocks": [
        {
          "id": "photographer_name",
          "type": "text",
          "content": "Иван Иванов",
          "order": 0
        },
        {
          "id": "avatar",
          "type": "image",
          "content": "https://picsum.photos/id/64/200/200",
          "order": 1
        },
        {
          "id": "bio",
          "type": "text",
          "content": "Профессиональный фотограф с 5-летним опытом. Специализируюсь на портретной и свадебной фотографии.",
          "order": 2
        },
        {
          "id": "portfolio_gallery",
          "type": "image",
          "content": "https://picsum.photos/id/26/800/600",
          "order": 3
        }
      ],
      "id": 2
    }
  ]
}